Empaquetado/Punto_8_Docstring.py
Empaquetado-1.0.dist-info/METADATA
Empaquetado-1.0.dist-info/WHEEL
Empaquetado-1.0.dist-info/top_level.txt
Empaquetado-1.0.dist-info/RECORD
