Metadata-Version: 2.1
Name: Empaquetado
Version: 1.0
Summary: Proyecto para obtener la última hora de acceso a una carpeta específica.
Author: Fiorella Salas Fonseca
Author-email: fiorellasalasfonseca670@gmail.com
License: GPL
